[
  {
    "name": "M1",
    "cost": 1.5,
    "handledProcess": {
      "P1": true, "P2": true
    }
  },
  {
    "name": "M2",
    "cost": 0.75,
    "handledProcess": {
      "P1": true
    }
  },
  {
    "name": "M3",
    "cost": 3.0,
    "handledProcess": {
      "P1": true, "P2": true, "P3": true
    }
  },
  {
    "name": "M4",
    "cost": 3.0,
    "handledProcess": {
      "P1": true, "P3": true
    }
  },
  {
    "name": "M5",
    "cost": 3.0,
    "handledProcess": {
      "P5": true
    }
  },
  {
    "name": "M6",
    "cost": 1.5,
    "handledProcess": {
      "P2": true, "P3": true
    }
  }
]